rich_notifier/__init__.py
rich_notifier/powershell_compatible.py
rich_notifier/rich_notifier.py
rich_notifier-0.1.0.dist-info/licenses/LICENSE
rich_notifier-0.1.0.dist-info/METADATA
rich_notifier-0.1.0.dist-info/WHEEL
rich_notifier-0.1.0.dist-info/top_level.txt
rich_notifier-0.1.0.dist-info/RECORD
