Metadata-Version: 2.4
Name: rich-notifier
Version: 0.1.0
Summary: 美观的终端通知库，基于 rich 实现彩色消息输出
Author-email: rich-notifier <marfirer@gmail.com>
License: MIT
Project-URL: Homepage, https://github.com/Iberxilong-blackbox/rich-notifier
Project-URL: Repository, https://github.com/Iberxilong-blackbox/rich-notifier.git
Project-URL: Issues, https://github.com/Iberxilong-blackbox/rich-notifier/issues
Keywords: terminal,notification,rich,color,logging
Classifier: Development Status :: 4 - Beta
Classifier: Intended Audience :: Developers
Classifier: License :: OSI Approved :: MIT License
Classifier: Programming Language :: Python :: 3
Classifier: Programming Language :: Python :: 3.8
Classifier: Programming Language :: Python :: 3.9
Classifier: Programming Language :: Python :: 3.10
Classifier: Programming Language :: Python :: 3.11
Classifier: Programming Language :: Python :: 3.12
Classifier: Topic :: Software Development :: Libraries :: Python Modules
Classifier: Topic :: System :: Logging
Classifier: Topic :: Terminals
Requires-Python: >=3.8
License-File: LICENSE
Requires-Dist: rich>=10.0.0
Provides-Extra: dev
Requires-Dist: pytest>=6.0; extra == "dev"
Requires-Dist: pytest-cov; extra == "dev"
Requires-Dist: black; extra == "dev"
Requires-Dist: isort; extra == "dev"
Requires-Dist: flake8; extra == "dev"
Dynamic: license-file
